f3dasm/__init__.py
f3dasm/design.py
f3dasm/hydra_tools.py
f3dasm/optimization.py
f3dasm/_src/__init__.py
f3dasm/_src/_io.py
f3dasm/_src/core.py
f3dasm/_src/datagenerator.py
f3dasm/_src/errors.py
f3dasm/_src/experimentdata.py
f3dasm/_src/experimentsample.py
f3dasm/_src/hydra_utils.py
f3dasm/_src/mpi_utils.py
f3dasm/_src/samplers.py
f3dasm/_src/datageneration/__init__.py
f3dasm/_src/datageneration/benchmarkfunctions.py
f3dasm/_src/datageneration/datagenerator_factory.py
f3dasm/_src/design/__init__.py
f3dasm/_src/design/domain.py
f3dasm/_src/design/parameter.py
f3dasm/_src/optimization/__init__.py
f3dasm/_src/optimization/_imports.py
f3dasm/_src/optimization/errors.py
f3dasm/_src/optimization/optimizer_factory.py
f3dasm/_src/optimization/optuna_implementations.py
f3dasm/_src/optimization/scipy_implementations.py
f3dasm/datageneration/__init__.py
f3dasm/datageneration/functions.py
f3dasm-2.2.1.dist-info/licenses/LICENSE
f3dasm-2.2.1.dist-info/METADATA
f3dasm-2.2.1.dist-info/WHEEL
f3dasm-2.2.1.dist-info/top_level.txt
f3dasm-2.2.1.dist-info/RECORD
