Metadata-Version: 2.4
Name: f3dasm
Version: 2.2.1
Summary: f3dasm - Framework for Data-driven Development and Analysis of Structures and Materials
Author-email: "M.P. van der Schelling" <m.p.vanderschelling@tudelft.nl>
Maintainer-email: "M.P. van der Schelling" <m.p.vanderschelling@tudelft.nl>
License: BSD-3-Clause
Project-URL: Documentation, https://f3dasm.readthedocs.io/
Project-URL: Repository, https://github.com/bessagroup/f3dasm
Classifier: License :: OSI Approved :: BSD License
Classifier: Development Status :: 5 - Production/Stable
Classifier: Intended Audience :: Developers
Classifier: Intended Audience :: Information Technology
Classifier: Intended Audience :: Science/Research
Classifier: Topic :: Scientific/Engineering :: Artificial Intelligence
Classifier: Topic :: Software Development :: Libraries :: Python Modules
Classifier: Programming Language :: Python :: 3.9
Classifier: Programming Language :: Python :: 3.10
Classifier: Programming Language :: Python :: 3.11
Classifier: Operating System :: Microsoft :: Windows
Classifier: Operating System :: POSIX :: Linux
Classifier: Operating System :: MacOS
Requires-Python: >=3.10
License-File: LICENSE
Requires-Dist: filelock>=3.16.1
Requires-Dist: hydra-core>=1.3.2
Requires-Dist: matplotlib>=3.7.5
Requires-Dist: numpy>=1.24.4
Requires-Dist: pandas>=2.0.3
Requires-Dist: pathos>=0.3.4
Requires-Dist: salib>=1.5.2
Requires-Dist: scipy>=1.10.1
Requires-Dist: xarray>=2023.1.0
Provides-Extra: all
Requires-Dist: abaqus2py>=1.0.0; extra == "all"
Requires-Dist: optuna>=4.4.0; extra == "all"
Provides-Extra: dev
Requires-Dist: pre-commit>=4.4.0; extra == "dev"
Provides-Extra: docs
Requires-Dist: mkdocs-gen-files>=0.5.0; extra == "docs"
Requires-Dist: mkdocs-include-exclude-files>=0.1.0; extra == "docs"
Requires-Dist: mkdocs-ipynb>=0.1.1; extra == "docs"
Requires-Dist: mkdocs-material>=9.6.20; extra == "docs"
Requires-Dist: mkdocstrings>=0.30.1; extra == "docs"
Requires-Dist: mkdocstrings-python>=1.18.2; extra == "docs"
Requires-Dist: pymdown-extensions>=10.16.1; extra == "docs"
Provides-Extra: test
Requires-Dist: hypothesis>=6.138.0; extra == "test"
Requires-Dist: pytest>=8.4.1; extra == "test"
Requires-Dist: pytest-cov>=6.2.1; extra == "test"
Dynamic: license-file
